[
    {
        "name": "Paniers de poisson Filet de parapluie de p\u00eache, Cage \u00e0 crevettes, filet de p\u00eache pliable",
        "current_price": "88.00",
        "price_before_discount": "169.00",
        "discount": "48%",
        "sizes": [],
        "features": [
            "Ce produit adopte un cadre de parapluie \u00e9pais. En l'utilisant, vous pouvez tirer le c\u00e2ble fermement et le coincer.",
            "il vous suffit d'appuyer sur la boucle pour r\u00e9tr\u00e9cir automatiquement pour le stockage.",
            "Il peut \u00eatre pos\u00e9 verticalement ou jet\u00e9 de mani\u00e8re rotative.",
            "SKU: GE232SE0G25PINAFAMZ",
            "Poids (kg): 1"
        ],
        "product_url": "https://www.jumia.ma/generic-paniers-de-poisson-filet-de-parapluie-de-peche-cage-a-crevettes-filet-de-peche-pliable-66547962.html",
        "image_url": "https://ma.jumia.is/unsafe/fit-in/680x680/filters:fill(white)/product/26/974566/1.jpg?3082",
        "stars": "0",
        "availability": "In Stock",
        "scraped_at": "2026-04-27T22:20:12.866736"
    },
    {
        "name": "But de football gonflable avec filet et ballon \u2013 Jeu d\u2019ext\u00e9rieur ou piscine",
        "current_price": "138.00",
        "price_before_discount": "210.00",
        "discount": "34%",
        "sizes": [],
        "features": [
            "Installation rapide et structure l\u00e9g\u00e8re \u00e0 transporter.",
            "Polyvalent\u202f: adapt\u00e9 pour le jardin, la piscine ou la plage.",
            "Vinyle r\u00e9sistant\u202f: supporte le jeu soutenu et l\u2019usage ext\u00e9rieur.",
            "Filet solide pour arr\u00eater les tirs et garantir la s\u00e9curit\u00e9.",
            "Ballon inclus pour jouer imm\u00e9diatement."
        ],
        "product_url": "https://www.jumia.ma/generic-but-de-football-gonflable-avec-filet-et-ballon-jeu-dexterieur-ou-piscine-67384026.html",
        "image_url": "https://ma.jumia.is/unsafe/fit-in/680x680/filters:fill(white)/product/62/048376/1.jpg?7199",
        "stars": "0",
        "availability": "In Stock",
        "scraped_at": "2026-04-27T22:20:13.504505"
    },
    {
        "name": "Filet de p\u00eache r\u00e9tractable avec accessoires \u2013 Id\u00e9al pour poissons et crustac\u00e9s",
        "current_price": "557.08",
        "price_before_discount": "779.91",
        "discount": "29%",
        "sizes": [],
        "features": [
            "SKU: GE232SE0PJLJCNAFAMZ",
            "Poids (kg): 1",
            "Couleur: Multicolour"
        ],
        "product_url": "https://www.jumia.ma/generic-filet-de-peche-retractable-avec-accessoires-ideal-pour-poissons-et-crustaces-67740924.html",
        "image_url": "https://ma.jumia.is/unsafe/fit-in/680x680/filters:fill(white)/product/42/904776/1.jpg?2264",
        "stars": "0",
        "availability": "In Stock",
        "scraped_at": "2026-04-27T22:20:14.027285"
    },
    {
        "name": "Filet de p\u00eache r\u00e9tractable avec accessoires \u2013 Id\u00e9al pour poissons et crustac\u00e9s",
        "current_price": "277.75",
        "price_before_discount": "388.85",
        "discount": "29%",
        "sizes": [],
        "features": [
            "SKU: GE232SE0898D8NAFAMZ",
            "Poids (kg): 1",
            "Couleur: Multicolour"
        ],
        "product_url": "https://www.jumia.ma/generic-filet-de-peche-retractable-avec-accessoires-ideal-pour-poissons-et-crustaces-67676831.html",
        "image_url": "https://ma.jumia.is/unsafe/fit-in/680x680/filters:fill(white)/product/13/867676/1.jpg?8450",
        "stars": "0",
        "availability": "In Stock",
        "scraped_at": "2026-04-27T22:20:14.595708"
    },
    {
        "name": "Filet de p\u00eache r\u00e9tractable avec accessoires \u2013 Id\u00e9al pour poissons et crustac\u00e9s",
        "current_price": "129.00",
        "price_before_discount": "322.00",
        "discount": "60%",
        "sizes": [],
        "features": [
            "Structure pliable et l\u00e9g\u00e8re : se d\u00e9ploie en quelques secondes et se range facilement.",
            "Entr\u00e9es multiples : augmentent l\u2019efficacit\u00e9 de capture en attirant les proies de plusieurs directions.",
            "Accessoires inclus : corde, flotteur, perles lumineuses et sac de transport pour une utilisation compl\u00e8te.",
            "Visibilit\u00e9 renforc\u00e9e : perles lumineuses pour rep\u00e9rer le pi\u00e8ge m\u00eame en faible luminosit\u00e9.",
            "SKU: GE232SE0MKHO8NAFAMZ"
        ],
        "product_url": "https://www.jumia.ma/generic-filet-de-peche-retractable-avec-accessoires-ideal-pour-poissons-et-crustaces-67570973.html",
        "image_url": "https://ma.jumia.is/unsafe/fit-in/680x680/filters:fill(white)/product/37/907576/1.jpg?8289",
        "stars": "0",
        "availability": "In Stock",
        "scraped_at": "2026-04-27T22:20:17.233767"
    },
    {
        "name": "topgym Filet de volleyball avec Ballon de volleyball Original Gratuit",
        "current_price": "1499.00",
        "price_before_discount": "",
        "discount": null,
        "sizes": [],
        "features": [
            "Mat\u00e9riau :\u00a0poly\u00e9thyl\u00e8ne de haute qualit\u00e9, haute r\u00e9sistance et r\u00e9sistance \u00e0 la d\u00e9chirure.",
            "Reliure en toile robuste, attrayante et durable.",
            "C\u00e2ble en acier a\u00e9ronautique et cordes de serrage, facile \u00e0 installer.",
            "Dimensions (L x l) : 32 x 3 cm",
            "Les diam\u00e8tre de filet\u00a0disponible : 1mm"
        ],
        "product_url": "https://www.jumia.ma/topgym-filet-de-volleyball-avec-ballon-de-volleyball-original-gratuit-65517572.html",
        "image_url": "https://ma.jumia.is/unsafe/fit-in/680x680/filters:fill(white)/product/27/571556/1.jpg?0343",
        "stars": "0",
        "availability": "-",
        "scraped_at": "2026-04-27T22:20:18.188338"
    },
    {
        "name": "Paniers de poisson Filet de parapluie de p\u00eache, Cage \u00e0 crevettes, filet de p\u00eache pliable",
        "current_price": "238.41",
        "price_before_discount": "333.77",
        "discount": "29%",
        "sizes": [],
        "features": [
            "SKU: GE232SE0CVYOKNAFAMZ",
            "Poids (kg): 1",
            "Couleur: Multicolour"
        ],
        "product_url": "https://www.jumia.ma/paniers-de-poisson-filet-de-parapluie-de-peche-cage-a-crevettes-filet-de-peche-pliable-generic-mpg1578604.html",
        "image_url": "https://ma.jumia.is/unsafe/fit-in/680x680/filters:fill(white)/product/21/646676/1.jpg?8639",
        "stars": "0",
        "availability": "In Stock",
        "scraped_at": "2026-04-27T22:20:18.922329"
    },
    {
        "name": "Paniers de poisson Filet de parapluie de p\u00eache, Cage \u00e0 crevettes, filet de p\u00eache pliable",
        "current_price": "494.17",
        "price_before_discount": "691.84",
        "discount": "29%",
        "sizes": [],
        "features": [
            "SKU: GE232SE0BNAQGNAFAMZ",
            "Poids (kg): 1",
            "Couleur: Multicolour"
        ],
        "product_url": "https://www.jumia.ma/paniers-de-poisson-filet-de-parapluie-de-peche-cage-a-crevettes-filet-de-peche-pliable-generic-mpg1590342.html",
        "image_url": "https://ma.jumia.is/unsafe/fit-in/680x680/filters:fill(white)/product/19/562776/1.jpg?2237",
        "stars": "0",
        "availability": "In Stock",
        "scraped_at": "2026-04-27T22:20:21.118105"
    }
]